adminactions/__init__.py
adminactions/actions.py
adminactions/api.py
adminactions/apps.py
adminactions/byrows_update.py
adminactions/compat.py
adminactions/exceptions.py
adminactions/export.py
adminactions/forms.py
adminactions/graph.py
adminactions/mass_update.py
adminactions/merge.py
adminactions/models.py
adminactions/signals.py
adminactions/urls.py
adminactions/utils.py
adminactions/views.py
adminactions/locale/en/LC_MESSAGES/django.po
adminactions/locale/es/LC_MESSAGES/django.po
adminactions/locale/fr/LC_MESSAGES/django.po
adminactions/locale/it/LC_MESSAGES/django.po
adminactions/locale/pl/LC_MESSAGES/django.po
adminactions/locale/pt_BR/LC_MESSAGES/django.po
adminactions/requirements/develop.pip
adminactions/requirements/install.py2.pip
adminactions/requirements/install.py3.pip
adminactions/static/adminactions/css/adminactions.css
adminactions/static/adminactions/css/adminactions.min.css
adminactions/static/adminactions/js/export.js
adminactions/static/adminactions/js/massupdate.js
adminactions/static/adminactions/js/merge.js
adminactions/static/adminactions/js/merge.min.js
adminactions/static/adminactions/js/jqplot/MIT-LICENSE.txt
adminactions/static/adminactions/js/jqplot/README.txt
adminactions/static/adminactions/js/jqplot/jquery.jqplot.css
adminactions/static/adminactions/js/jqplot/jquery.jqplot.min.css
adminactions/static/adminactions/js/jqplot/jquery.jqplot.min.js
adminactions/static/adminactions/js/jqplot/plugins/jqplot.barRenderer.js
adminactions/static/adminactions/js/jqplot/plugins/jqplot.barRenderer.min.js
adminactions/static/adminactions/js/jqplot/plugins/jqplot.categoryAxisRenderer.js
adminactions/static/adminactions/js/jqplot/plugins/jqplot.categoryAxisRenderer.min.js
adminactions/static/adminactions/js/jqplot/plugins/jqplot.pieRenderer.js
adminactions/static/adminactions/js/jqplot/plugins/jqplot.pieRenderer.min.js
adminactions/templates/500.html
adminactions/templates/adminactions/any_model.html
django_adminactions_ptBR-1.9.0.dist-info/AUTHORS.rst
django_adminactions_ptBR-1.9.0.dist-info/LICENSE
django_adminactions_ptBR-1.9.0.dist-info/METADATA
django_adminactions_ptBR-1.9.0.dist-info/WHEEL
django_adminactions_ptBR-1.9.0.dist-info/top_level.txt
django_adminactions_ptBR-1.9.0.dist-info/RECORD
