Metadata-Version: 2.1
Name: django-adminactions-ptBR
Version: 1.9.0
Summary: Collections of useful actions to use with django.contrib.admin.ModelAdmin
Home-page: https://github.com/AlexandreProenca/django-adminactions
Author: sax
Author-email: alexandre.proenca@hotmail.com.br
License: MIT
Download-URL: https://github.com/AlexandreProenca/django-adminactions
Platform: any
Classifier: Environment :: Web Environment
Classifier: Framework :: Django
Classifier: Operating System :: OS Independent
Classifier: Framework :: Django :: 2.2
Classifier: Framework :: Django :: 3.0
Classifier: Framework :: Django :: 3.1
Classifier: Programming Language :: Python :: 3.6
Classifier: Programming Language :: Python :: 3.7
Classifier: Programming Language :: Python :: 3.8
Classifier: Programming Language :: Python :: 3.9
Classifier: Intended Audience :: Developers
Requires-Dist: pytz
Requires-Dist: xlrd (>=0.9.2)
Requires-Dist: xlwt
Provides-Extra: dev
Requires-Dist: check-manifest ; extra == 'dev'
Requires-Dist: django-dynamic-fixture ; extra == 'dev'
Requires-Dist: django-webtest ; extra == 'dev'
Requires-Dist: docutils ; extra == 'dev'
Requires-Dist: flake8 ; extra == 'dev'
Requires-Dist: isort ; extra == 'dev'
Requires-Dist: mock (>=1.0.1) ; extra == 'dev'
Requires-Dist: modernize ; extra == 'dev'
Requires-Dist: pdbpp ; extra == 'dev'
Requires-Dist: pillow ; extra == 'dev'
Requires-Dist: pytest ; extra == 'dev'
Requires-Dist: pytest-cache ; extra == 'dev'
Requires-Dist: pytest-cov ; extra == 'dev'
Requires-Dist: pytest-django ; extra == 'dev'
Requires-Dist: pytest-echo ; extra == 'dev'
Requires-Dist: pytest-pythonpath ; extra == 'dev'
Requires-Dist: readme ; extra == 'dev'
Requires-Dist: selenium (>=2.42.0) ; extra == 'dev'
Requires-Dist: setuptools (>=15.0) ; extra == 'dev'
Requires-Dist: tox ; extra == 'dev'
Requires-Dist: virtualenv ; extra == 'dev'
Requires-Dist: wheel ; extra == 'dev'
Provides-Extra: test
Requires-Dist: check-manifest ; extra == 'test'
Requires-Dist: django-dynamic-fixture ; extra == 'test'
Requires-Dist: django-webtest ; extra == 'test'
Requires-Dist: flake8 ; extra == 'test'
Requires-Dist: mock (>=1.0.1) ; extra == 'test'
Requires-Dist: modernize ; extra == 'test'
Requires-Dist: pillow ; extra == 'test'
Requires-Dist: pytest ; extra == 'test'
Requires-Dist: pytest-cache ; extra == 'test'
Requires-Dist: pytest-cov ; extra == 'test'
Requires-Dist: pytest-django ; extra == 'test'
Requires-Dist: pytest-echo ; extra == 'test'
Requires-Dist: pytest-pythonpath ; extra == 'test'
Requires-Dist: pytz ; extra == 'test'
Requires-Dist: readme ; extra == 'test'
Requires-Dist: selenium (>=2.42.0) ; extra == 'test'
Requires-Dist: setuptools (>=15.0) ; extra == 'test'
Requires-Dist: tox ; extra == 'test'
Requires-Dist: xlrd (>=0.9.2) ; extra == 'test'
Requires-Dist: xlwt ; extra == 'test'
